[
    { 
        "rangeIP": ".1 - .10" 
    }, 
    { 
        "rangeIP": ".11 - .20" 
    }, 
    { 
        "rangeIP": ".21 - .30" 
    }, 
    { 
        "rangeIP": ".31 - .40"
     },
    { 
        "rangeIP": ".41 - .50" 
    }, 
    { 
        "rangeIP": ".51 - .60" 
    }, 
    { 
        "rangeIP": ".61 - .70" 
    }, 
    { 
        "rangeIP": ".71 - .80" 
    }, 
    { 
        "rangeIP": ".81 - .90" 
    }, 
    { 
        "rangeIP": ".91 - .100" 
    }, 
    { 
        "rangeIP": ".101 - .110" 
    }, 
    { 
        "rangeIP": ".111 - .120"
     },
    { 
        "rangeIP": ".121 - .130" 
    }, 
    { 
        "rangeIP": ".131 - .140" 
    }, 
    { 
        "rangeIP": ".141 - .150" 
    }, 
    { 
        "rangeIP": ".151 - .160" 
    }, 
    { 
        "rangeIP": ".171 - .180" 
    }, 
    { 
        "rangeIP": ".181 - .190" 
    }, 
    { 
        "rangeIP": ".191 - .200" 
    }, 
    { 
        "rangeIP": ".201 - .210" 
    },  
    { 
        "rangeIP": ".211 - .220" 
    }, 
    { 
        "rangeIP": ".221 - .230" 
    }, 
    { 
        "rangeIP": ".231 - .240" 
    }, 
    { 
        "rangeIP": ".241 - .250" 
    }, 
    { 
        "rangeIP": ".251 - .254" 
    }
]